pdf_section_sentiment/__init__.py
pdf_section_sentiment/extract_pdf.py
pdf_section_sentiment/sentiment.py
pdf_section_sentiment/utils.py
pdf_section_sentiment-0.1.5.dist-info/licenses/LICENSE
pdf_section_sentiment-0.1.5.dist-info/METADATA
pdf_section_sentiment-0.1.5.dist-info/WHEEL
pdf_section_sentiment-0.1.5.dist-info/entry_points.txt
pdf_section_sentiment-0.1.5.dist-info/top_level.txt
pdf_section_sentiment-0.1.5.dist-info/RECORD
