Metadata-Version: 2.4
Name: pdf-section-sentiment
Version: 0.1.5
Summary: Extract sections from PDFs and perform sentiment analysis
Author-email: Sanjay BK <krishsan1963@gmail.com>
Project-URL: Homepage, https://github.com/sanjaybk7/pdf-section-sentiment
License-File: LICENSE
Requires-Dist: docling
Requires-Dist: markdown
Requires-Dist: textblob
Requires-Dist: pandas
Requires-Dist: langchain-text-splitters
Dynamic: license-file
